ticketbis/__init__.py
ticketbis/tests/__init__.py
ticketbis/tests/_creds.example.py
ticketbis/tests/test_categories.py
ticketbis/tests/test_events.py
ticketbis/tests/test_oauth.py
ticketbis/tests/test_schemas.py
ticketbis/tests/test_section_groups.py
ticketbis/tests/test_sites.py
ticketbis/tests/test_venues.py
ticketbis-0.3.5.dist-info/LICENSE
ticketbis-0.3.5.dist-info/METADATA
ticketbis-0.3.5.dist-info/WHEEL
ticketbis-0.3.5.dist-info/top_level.txt
ticketbis-0.3.5.dist-info/zip-safe
ticketbis-0.3.5.dist-info/RECORD
