Metadata-Version: 2.1
Name: ticketbis
Version: 0.3.5
Summary: ticketbis API wrapper library
Home-page: https://github.com/ticketbis/ticketbis-python-api-client
Author: Jose Gargallo
Author-email: jose.gargallo@ticketbis.com
License: MIT License
Download-URL: https://github.com/ticketbis/ticketbis-python-api-client
Keywords: ticketbis api
Platform: UNKNOWN
Classifier: Development Status :: 5 - Production/Stable
Classifier: Intended Audience :: Developers
Classifier: Natural Language :: English
Classifier: Operating System :: OS Independent
Classifier: Programming Language :: Python
Classifier: Topic :: Internet :: WWW/HTTP :: Dynamic Content
Classifier: License :: OSI Approved :: MIT License
Requires-Dist: requests (>=2.1)
Requires-Dist: six
